LICENSE
requirements.txt
ru_proverbs/__init__.py
ru_proverbs/__main__.py
ru_proverbs/generator.py
ru_proverbs/py.typed
ru_proverbs/ru_proverbs.txt
ru_proverbs/ru_proverbs_chars_config.json
ru_proverbs/ru_proverbs_chars_vocab.json
ru_proverbs/ru_proverbs_chars_weights.hdf5
ru_proverbs-1.2.0.dist-info/LICENSE
ru_proverbs-1.2.0.dist-info/WHEEL
ru_proverbs-1.2.0.dist-info/METADATA
ru_proverbs-1.2.0.dist-info/entry_points.txt
ru_proverbs-1.2.0.dist-info/RECORD
