Metadata-Version: 2.1
Name: ru-proverbs
Version: 1.2.0
Summary: Russian Proverbs AI-powered proverbs generator.
Home-page: https://github.com/xSAVIKx/ru-proverbs
License: Apache-2.0
Keywords: python,textgenrnn,ML,AI,tensorflow
Author: Yurii Serhiichuk
Author-email: savik.ne@gmail.com
Requires-Python: >=3.10.0,<3.11.0
Classifier: Intended Audience :: Developers
Classifier: License :: OSI Approved :: Apache Software License
Classifier: Operating System :: OS Independent
Classifier: Programming Language :: Python
Classifier: Programming Language :: Python :: 3
Classifier: Programming Language :: Python :: 3.10
Classifier: Programming Language :: Python :: 3
Classifier: Programming Language :: Python :: 3.10
Classifier: Programming Language :: Python :: 3.8
Classifier: Programming Language :: Python :: 3.9
Requires-Dist: tensorflow (>=2.3.1,<3.0.0)
Requires-Dist: textgenrnn (>=2.0.0,<3.0.0)
Project-URL: Bug Tracker, https://github.com/xSAVIKx/ru-proverbs/issues
Project-URL: Repository, https://github.com/xSAVIKx/ru-proverbs
